nzbget_file_opener/__init__.py
nzbget_file_opener/app.py
nzbget_file_opener/args.py
nzbget_file_opener/config.py
nzbget_file_opener/nzbget.py
nzbget_file_opener/upload.py
nzbget_file_opener-1.0.3.dist-info/METADATA
nzbget_file_opener-1.0.3.dist-info/WHEEL
nzbget_file_opener-1.0.3.dist-info/entry_points.txt
nzbget_file_opener-1.0.3.dist-info/top_level.txt
nzbget_file_opener-1.0.3.dist-info/RECORD
