Metadata-Version: 2.1
Name: nzbget-file-opener
Version: 1.0.3
Summary: nzbget-file-opener allows you to download *.nzb files with just a double click
Home-page: http://github.com/bil0u/nzbget-file-opener
Author: Ugo Popée
Author-email: ugo.popee@me.com
License: MIT
Keywords: nzbget-file-opener nzbget extension
Platform: UNKNOWN
Classifier: Development Status :: 3 - Alpha
Classifier: License :: OSI Approved :: MIT License
Classifier: Programming Language :: Python :: 3.7
Classifier: Topic :: Text Processing :: Linguistic
Requires-Python: >=3.6
Requires-Dist: pytest
Requires-Dist: psutil
